[
  {
    "id": "cs_0",
    "name": "5115 Calacatta Stillstorm - Quartz Worktop",
    "category": "Quartz",
    "texture": "Polished",
    "swatchUrl": "/stones/5115_calacatta_stillstorm___quartz_worktop.jpg",
    "description": "LJSTONE texture of 5115 Calacatta Stillstorm - Quartz Worktop surface, Quartz, Polished finish, high quality stone texture."
  },
  {
    "id": "cs_1",
    "name": "5116 Calacatta Nectar - Quartz Worktop",
    "category": "Quartz",
    "texture": "Polished",
    "swatchUrl": "/stones/5116_calacatta_nectar___quartz_worktop.jpg",
    "description": "LJSTONE texture of 5116 Calacatta Nectar - Quartz Worktop surface, Quartz, Polished finish, high quality stone texture."
  },
  {
    "id": "cs_2",
    "name": "508 Isobellia - Porcelain Worktop",
    "category": "Quartz",
    "texture": "Polished",
    "swatchUrl": "/stones/508_isobellia___porcelain_worktop.jpg",
    "description": "LJSTONE texture of 508 Isobellia - Porcelain Worktop surface, Quartz, Polished finish, high quality stone texture."
  },
  {
    "id": "cs_3",
    "name": "8151 Moonflow - Fusion Worktop",
    "category": "Quartz",
    "texture": "ICON",
    "swatchUrl": "/stones/8151_moonflow___fusion_worktop.jpg",
    "description": "LJSTONE texture of 8151 Moonflow - Fusion Worktop surface, Quartz, ICON finish, high quality stone texture."
  },
  {
    "id": "cs_4",
    "name": "5110 Alpine Mist - Fusion Worktop",
    "category": "Quartz",
    "texture": "ICON",
    "swatchUrl": "/stones/5110_alpine_mist___fusion_worktop.jpg",
    "description": "LJSTONE texture of 5110 Alpine Mist - Fusion Worktop surface, Quartz, ICON finish, high quality stone texture."
  },
  {
    "id": "cs_5",
    "name": "5310 Brillianza - Fusion Worktop",
    "category": "Quartz",
    "texture": "ICON",
    "swatchUrl": "/stones/5310_brillianza___fusion_worktop.jpg",
    "description": "LJSTONE texture of 5310 Brillianza - Fusion Worktop surface, Quartz, ICON finish, high quality stone texture."
  },
  {
    "id": "cs_6",
    "name": "550 Silvax - Porcelain Worktop",
    "category": "Quartz",
    "texture": "Polished",
    "swatchUrl": "/stones/550_silvax___porcelain_worktop.jpg",
    "description": "LJSTONE texture of 550 Silvax - Porcelain Worktop surface, Quartz, Polished finish, high quality stone texture."
  },
  {
    "id": "cs_7",
    "name": "543 Marenstone - Porcelain Worktop",
    "category": "Quartz",
    "texture": "Polished",
    "swatchUrl": "/stones/543_marenstone___porcelain_worktop.jpg",
    "description": "LJSTONE texture of 543 Marenstone - Porcelain Worktop surface, Quartz, Polished finish, high quality stone texture."
  },
  {
    "id": "cs_8",
    "name": "542 Mosstone - Porcelain Worktop",
    "category": "Quartz",
    "texture": "Polished",
    "swatchUrl": "/stones/542_mosstone___porcelain_worktop.jpg",
    "description": "LJSTONE texture of 542 Mosstone - Porcelain Worktop surface, Quartz, Polished finish, high quality stone texture."
  },
  {
    "id": "cs_9",
    "name": "8477 Ocean Sage - Fusion Worktop",
    "category": "Quartz",
    "texture": "ICON",
    "swatchUrl": "/stones/8477_ocean_sage___fusion_worktop.jpg",
    "description": "LJSTONE texture of 8477 Ocean Sage - Fusion Worktop surface, Quartz, ICON finish, high quality stone texture."
  },
  {
    "id": "cs_10",
    "name": "2141 Snow - Quartz Worktop",
    "category": "Quartz",
    "texture": "Polished",
    "swatchUrl": "/stones/2141_snow___quartz_worktop.jpg",
    "description": "LJSTONE texture of 2141 Snow - Quartz Worktop surface, Quartz, Polished finish, high quality stone texture."
  },
  {
    "id": "cs_11",
    "name": "4600 Organic White - Quartz Worktop",
    "category": "Quartz",
    "texture": "Polished",
    "swatchUrl": "/stones/4600_organic_white___quartz_worktop.jpg",
    "description": "LJSTONE texture of 4600 Organic White - Quartz Worktop surface, Quartz, Polished finish, high quality stone texture."
  },
  {
    "id": "cs_12",
    "name": "1141 Pure White - Quartz Worktop",
    "category": "Quartz",
    "texture": "Polished",
    "swatchUrl": "/stones/1141_pure_white___quartz_worktop.jpg",
    "description": "LJSTONE texture of 1141 Pure White - Quartz Worktop surface, Quartz, Polished finish, high quality stone texture."
  },
  {
    "id": "cs_13",
    "name": "503 Circa - Porcelain Worktop",
    "category": "Quartz",
    "texture": "Polished",
    "swatchUrl": "/stones/503_circa___porcelain_worktop.jpg",
    "description": "LJSTONE texture of 503 Circa - Porcelain Worktop surface, Quartz, Polished finish, high quality stone texture."
  },
  {
    "id": "cs_14",
    "name": "5112 Aterra Blanca - Quartz Worktop",
    "category": "Quartz",
    "texture": "Polished",
    "swatchUrl": "/stones/5112_aterra_blanca___quartz_worktop.jpg",
    "description": "LJSTONE texture of 5112 Aterra Blanca - Quartz Worktop surface, Quartz, Polished finish, high quality stone texture."
  },
  {
    "id": "cs_15",
    "name": "6141 Ocean Foam - Quartz Worktop",
    "category": "Quartz",
    "texture": "Polished",
    "swatchUrl": "/stones/6141_ocean_foam___quartz_worktop.jpg",
    "description": "LJSTONE texture of 6141 Ocean Foam - Quartz Worktop surface, Quartz, Polished finish, high quality stone texture."
  },
  {
    "id": "cs_16",
    "name": "5113 Solenna - Fusion Worktop",
    "category": "Quartz",
    "texture": "ICON",
    "swatchUrl": "/stones/5113_solenna___fusion_worktop.jpg",
    "description": "LJSTONE texture of 5113 Solenna - Fusion Worktop surface, Quartz, ICON finish, high quality stone texture."
  },
  {
    "id": "cs_17",
    "name": "5151 Empira White - Quartz Worktop",
    "category": "Quartz",
    "texture": "Polished",
    "swatchUrl": "/stones/5151_empira_white___quartz_worktop.jpg",
    "description": "LJSTONE texture of 5151 Empira White - Quartz Worktop surface, Quartz, Polished finish, high quality stone texture."
  },
  {
    "id": "cs_18",
    "name": "5141 Frosty Carrina - Fusion Worktop",
    "category": "Quartz",
    "texture": "ICON",
    "swatchUrl": "/stones/5141_frosty_carrina___fusion_worktop.jpg",
    "description": "LJSTONE texture of 5141 Frosty Carrina - Fusion Worktop surface, Quartz, ICON finish, high quality stone texture."
  },
  {
    "id": "cs_19",
    "name": "507 Marbannova - Porcelain Worktop",
    "category": "Quartz",
    "texture": "Polished",
    "swatchUrl": "/stones/507_marbannova___porcelain_worktop.jpg",
    "description": "LJSTONE texture of 507 Marbannova - Porcelain Worktop surface, Quartz, Polished finish, high quality stone texture."
  },
  {
    "id": "cs_20",
    "name": "581 Lucillia - Porcelain Worktop",
    "category": "Quartz",
    "texture": "Polished",
    "swatchUrl": "/stones/581_lucillia___porcelain_worktop.jpg",
    "description": "LJSTONE texture of 581 Lucillia - Porcelain Worktop surface, Quartz, Polished finish, high quality stone texture."
  },
  {
    "id": "cs_21",
    "name": "504 Lumena - Porcelain Worktop",
    "category": "Quartz",
    "texture": "Polished",
    "swatchUrl": "/stones/504_lumena___porcelain_worktop.jpg",
    "description": "LJSTONE texture of 504 Lumena - Porcelain Worktop surface, Quartz, Polished finish, high quality stone texture."
  },
  {
    "id": "cs_22",
    "name": "5121 Layalite - Quartz Worktop",
    "category": "Quartz",
    "texture": "Polished",
    "swatchUrl": "/stones/5121_layalite___quartz_worktop.jpg",
    "description": "LJSTONE texture of 5121 Layalite - Quartz Worktop surface, Quartz, Polished finish, high quality stone texture."
  },
  {
    "id": "cs_23",
    "name": "110 Whitenna - Porcelain Worktop",
    "category": "Quartz",
    "texture": "Polished",
    "swatchUrl": "/stones/110_whitenna___porcelain_worktop.jpg",
    "description": "LJSTONE texture of 110 Whitenna - Porcelain Worktop surface, Quartz, Polished finish, high quality stone texture."
  },
  {
    "id": "cs_24",
    "name": "531 Libretta - Porcelain Worktop",
    "category": "Quartz",
    "texture": "Polished",
    "swatchUrl": "/stones/531_libretta___porcelain_worktop.jpg",
    "description": "LJSTONE texture of 531 Libretta - Porcelain Worktop surface, Quartz, Polished finish, high quality stone texture."
  },
  {
    "id": "cs_25",
    "name": "501 Snowdrift - Porcelain Worktop",
    "category": "Quartz",
    "texture": "Polished",
    "swatchUrl": "/stones/501_snowdrift___porcelain_worktop.jpg",
    "description": "LJSTONE texture of 501 Snowdrift - Porcelain Worktop surface, Quartz, Polished finish, high quality stone texture."
  },
  {
    "id": "cs_26",
    "name": "5171 Arabetto - Fusion Worktop",
    "category": "Quartz",
    "texture": "ICON",
    "swatchUrl": "/stones/5171_arabetto___fusion_worktop.jpg",
    "description": "LJSTONE texture of 5171 Arabetto - Fusion Worktop surface, Quartz, ICON finish, high quality stone texture."
  },
  {
    "id": "cs_27",
    "name": "4001 Fresh Concrete - Quartz Worktop",
    "category": "Quartz",
    "texture": "Polished",
    "swatchUrl": "/stones/4001_fresh_concrete___quartz_worktop.jpg",
    "description": "LJSTONE texture of 4001 Fresh Concrete - Quartz Worktop surface, Quartz, Polished finish, high quality stone texture."
  },
  {
    "id": "cs_28",
    "name": "5140 Dreamy Carrara - Fusion Worktop",
    "category": "Quartz",
    "texture": "ICON",
    "swatchUrl": "/stones/5140_dreamy_carrara___fusion_worktop.jpg",
    "description": "LJSTONE texture of 5140 Dreamy Carrara - Fusion Worktop surface, Quartz, ICON finish, high quality stone texture."
  },
  {
    "id": "cs_29",
    "name": "505 Archetta - Porcelain Worktop",
    "category": "Quartz",
    "texture": "Polished",
    "swatchUrl": "/stones/505_archetta___porcelain_worktop.jpg",
    "description": "LJSTONE texture of 505 Archetta - Porcelain Worktop surface, Quartz, Polished finish, high quality stone texture."
  },
  {
    "id": "cs_30",
    "name": "5000 London Grey - Quartz Worktop",
    "category": "Quartz",
    "texture": "Polished",
    "swatchUrl": "/stones/5000_london_grey___quartz_worktop.jpg",
    "description": "LJSTONE texture of 5000 London Grey - Quartz Worktop surface, Quartz, Polished finish, high quality stone texture."
  },
  {
    "id": "cs_31",
    "name": "5131 Calacatta Nuvo - Fusion Worktop",
    "category": "Quartz",
    "texture": "ICON",
    "swatchUrl": "/stones/5131_calacatta_nuvo___fusion_worktop.jpg",
    "description": "LJSTONE texture of 5131 Calacatta Nuvo - Fusion Worktop surface, Quartz, ICON finish, high quality stone texture."
  },
  {
    "id": "cs_32",
    "name": "506 Mirabel - Porcelain Worktop",
    "category": "Quartz",
    "texture": "Polished",
    "swatchUrl": "/stones/506_mirabel___porcelain_worktop.jpg",
    "description": "LJSTONE texture of 506 Mirabel - Porcelain Worktop surface, Quartz, Polished finish, high quality stone texture."
  },
  {
    "id": "cs_33",
    "name": "4141 Misty Carrera - Quartz Worktop",
    "category": "Quartz",
    "texture": "Polished",
    "swatchUrl": "/stones/4141_misty_carrera___quartz_worktop.jpg",
    "description": "LJSTONE texture of 4141 Misty Carrera - Quartz Worktop surface, Quartz, Polished finish, high quality stone texture."
  },
  {
    "id": "cs_34",
    "name": "1001 Riverlet - Mineral Worktop",
    "category": "Quartz",
    "texture": "Low silica",
    "swatchUrl": "/stones/1001_riverlet___mineral_worktop.jpg",
    "description": "LJSTONE texture of 1001 Riverlet - Mineral Worktop surface, Quartz, Low silica finish, high quality stone texture."
  },
  {
    "id": "cs_35",
    "name": "4011 Cloudburst Concrete - Fusion Worktop",
    "category": "Quartz",
    "texture": "ICON",
    "swatchUrl": "/stones/4011_cloudburst_concrete___fusion_worktop.jpg",
    "description": "LJSTONE texture of 4011 Cloudburst Concrete - Fusion Worktop surface, Quartz, ICON finish, high quality stone texture."
  },
  {
    "id": "cs_36",
    "name": "5031 Statuario Maximus - Quartz Worktop",
    "category": "Quartz",
    "texture": "Polished",
    "swatchUrl": "/stones/5031_statuario_maximus___quartz_worktop.jpg",
    "description": "LJSTONE texture of 5031 Statuario Maximus - Quartz Worktop surface, Quartz, Polished finish, high quality stone texture."
  },
  {
    "id": "cs_37",
    "name": "5143 White Attica - Quartz Worktop",
    "category": "Quartz",
    "texture": "Polished",
    "swatchUrl": "/stones/5143_white_attica___quartz_worktop.jpg",
    "description": "LJSTONE texture of 5143 White Attica - Quartz Worktop surface, Quartz, Polished finish, high quality stone texture."
  },
  {
    "id": "cs_38",
    "name": "413 White Ciment - Porcelain Worktop",
    "category": "Quartz",
    "texture": "Polished",
    "swatchUrl": "/stones/413_white_ciment___porcelain_worktop.jpg",
    "description": "LJSTONE texture of 413 White Ciment - Porcelain Worktop surface, Quartz, Polished finish, high quality stone texture."
  },
  {
    "id": "cs_39",
    "name": "502 Sleet - Porcelain Worktop",
    "category": "Quartz",
    "texture": "Polished",
    "swatchUrl": "/stones/502_sleet___porcelain_worktop.jpg",
    "description": "LJSTONE texture of 502 Sleet - Porcelain Worktop surface, Quartz, Polished finish, high quality stone texture."
  },
  {
    "id": "cs_40",
    "name": "4601 Frozen Terra - Quartz Worktop",
    "category": "Quartz",
    "texture": "Polished",
    "swatchUrl": "/stones/4601_frozen_terra___quartz_worktop.jpg",
    "description": "LJSTONE texture of 4601 Frozen Terra - Quartz Worktop surface, Quartz, Polished finish, high quality stone texture."
  },
  {
    "id": "cs_41",
    "name": "6131 Bianco Drift - Quartz Worktop",
    "category": "Quartz",
    "texture": "Polished",
    "swatchUrl": "/stones/6131_bianco_drift___quartz_worktop.jpg",
    "description": "LJSTONE texture of 6131 Bianco Drift - Quartz Worktop surface, Quartz, Polished finish, high quality stone texture."
  },
  {
    "id": "cs_42",
    "name": "6046 Moorland Fog - Quartz Worktop",
    "category": "Quartz",
    "texture": "Polished",
    "swatchUrl": "/stones/6046_moorland_fog___quartz_worktop.jpg",
    "description": "LJSTONE texture of 6046 Moorland Fog - Quartz Worktop surface, Quartz, Polished finish, high quality stone texture."
  },
  {
    "id": "cs_43",
    "name": "4230 Shitake - Quartz Worktop",
    "category": "Quartz",
    "texture": "Polished",
    "swatchUrl": "/stones/4230_shitake___quartz_worktop.jpg",
    "description": "LJSTONE texture of 4230 Shitake - Quartz Worktop surface, Quartz, Polished finish, high quality stone texture."
  },
  {
    "id": "cs_44",
    "name": "5212 Taj Royale - Quartz Worktop",
    "category": "Quartz",
    "texture": "Polished",
    "swatchUrl": "/stones/5212_taj_royale___quartz_worktop.jpg",
    "description": "LJSTONE texture of 5212 Taj Royale - Quartz Worktop surface, Quartz, Polished finish, high quality stone texture."
  },
  {
    "id": "cs_45",
    "name": "4023 Topus Concrete - Quartz Worktop",
    "category": "Quartz",
    "texture": "Polished",
    "swatchUrl": "/stones/4023_topus_concrete___quartz_worktop.jpg",
    "description": "LJSTONE texture of 4023 Topus Concrete - Quartz Worktop surface, Quartz, Polished finish, high quality stone texture."
  },
  {
    "id": "cs_46",
    "name": "512 Transcenda - Porcelain Worktop",
    "category": "Quartz",
    "texture": "Polished",
    "swatchUrl": "/stones/512_transcenda___porcelain_worktop.jpg",
    "description": "LJSTONE texture of 512 Transcenda - Porcelain Worktop surface, Quartz, Polished finish, high quality stone texture."
  },
  {
    "id": "cs_47",
    "name": "1002 Wyndigo - Mineral Worktop",
    "category": "Quartz",
    "texture": "Low silica",
    "swatchUrl": "/stones/1002_wyndigo___mineral_worktop.jpg",
    "description": "LJSTONE texture of 1002 Wyndigo - Mineral Worktop surface, Quartz, Low silica finish, high quality stone texture."
  },
  {
    "id": "cs_48",
    "name": "580 Fume - Porcelain Worktop",
    "category": "Quartz",
    "texture": "Polished",
    "swatchUrl": "/stones/580_fume___porcelain_worktop.jpg",
    "description": "LJSTONE texture of 580 Fume - Porcelain Worktop surface, Quartz, Polished finish, high quality stone texture."
  },
  {
    "id": "cs_49",
    "name": "410 Aluminous - Porcelain Worktop",
    "category": "Quartz",
    "texture": "Polished",
    "swatchUrl": "/stones/410_aluminous___porcelain_worktop.jpg",
    "description": "LJSTONE texture of 410 Aluminous - Porcelain Worktop surface, Quartz, Polished finish, high quality stone texture."
  },
  {
    "id": "cs_50",
    "name": "4044 Airy Concrete - Fusion Worktop",
    "category": "Quartz",
    "texture": "ICON",
    "swatchUrl": "/stones/4044_airy_concrete___fusion_worktop.jpg",
    "description": "LJSTONE texture of 4044 Airy Concrete - Fusion Worktop surface, Quartz, ICON finish, high quality stone texture."
  },
  {
    "id": "cs_51",
    "name": "4043 Primordia - Quartz Worktop",
    "category": "Quartz",
    "texture": "Polished",
    "swatchUrl": "/stones/4043_primordia___quartz_worktop.jpg",
    "description": "LJSTONE texture of 4043 Primordia - Quartz Worktop surface, Quartz, Polished finish, high quality stone texture."
  },
  {
    "id": "cs_52",
    "name": "4130 Clamshell - Quartz Worktop",
    "category": "Quartz",
    "texture": "Polished",
    "swatchUrl": "/stones/4130_clamshell___quartz_worktop.jpg",
    "description": "LJSTONE texture of 4130 Clamshell - Quartz Worktop surface, Quartz, Polished finish, high quality stone texture."
  },
  {
    "id": "cs_53",
    "name": "4030 Pebble - Quartz Worktop",
    "category": "Quartz",
    "texture": "Polished",
    "swatchUrl": "/stones/4030_pebble___quartz_worktop.jpg",
    "description": "LJSTONE texture of 4030 Pebble - Quartz Worktop surface, Quartz, Polished finish, high quality stone texture."
  },
  {
    "id": "cs_54",
    "name": "4004 Raw Concrete - Quartz Worktop",
    "category": "Quartz",
    "texture": "Polished",
    "swatchUrl": "/stones/4004_raw_concrete___quartz_worktop.jpg",
    "description": "LJSTONE texture of 4004 Raw Concrete - Quartz Worktop surface, Quartz, Polished finish, high quality stone texture."
  },
  {
    "id": "cs_55",
    "name": "544 Auralux - Porcelain Worktop",
    "category": "Quartz",
    "texture": "Polished",
    "swatchUrl": "/stones/544_auralux___porcelain_worktop.jpg",
    "description": "LJSTONE texture of 544 Auralux - Porcelain Worktop surface, Quartz, Polished finish, high quality stone texture."
  },
  {
    "id": "cs_56",
    "name": "6313 Turbine Grey - Mineral Worktop",
    "category": "Quartz",
    "texture": "Low silica",
    "swatchUrl": "/stones/6313_turbine_grey___mineral_worktop.jpg",
    "description": "LJSTONE texture of 6313 Turbine Grey - Mineral Worktop surface, Quartz, Low silica finish, high quality stone texture."
  },
  {
    "id": "cs_57",
    "name": "513 Striata - Porcelain Worktop",
    "category": "Quartz",
    "texture": "Polished",
    "swatchUrl": "/stones/513_striata___porcelain_worktop.jpg",
    "description": "LJSTONE texture of 513 Striata - Porcelain Worktop surface, Quartz, Polished finish, high quality stone texture."
  },
  {
    "id": "cs_58",
    "name": "5133 Symphony Grey - Quartz Worktop",
    "category": "Quartz",
    "texture": "Polished",
    "swatchUrl": "/stones/5133_symphony_grey___quartz_worktop.jpg",
    "description": "LJSTONE texture of 5133 Symphony Grey - Quartz Worktop surface, Quartz, Polished finish, high quality stone texture."
  },
  {
    "id": "cs_59",
    "name": "411 Concrita - Porcelain Worktop",
    "category": "Quartz",
    "texture": "Polished",
    "swatchUrl": "/stones/411_concrita___porcelain_worktop.jpg",
    "description": "LJSTONE texture of 411 Concrita - Porcelain Worktop surface, Quartz, Polished finish, high quality stone texture."
  },
  {
    "id": "cs_60",
    "name": "516 Locura - Porcelain Worktop",
    "category": "Quartz",
    "texture": "Polished",
    "swatchUrl": "/stones/516_locura___porcelain_worktop.jpg",
    "description": "LJSTONE texture of 516 Locura - Porcelain Worktop surface, Quartz, Polished finish, high quality stone texture."
  },
  {
    "id": "cs_61",
    "name": "4033 Rugged Concrete - Fusion Worktop",
    "category": "Quartz",
    "texture": "ICON",
    "swatchUrl": "/stones/4033_rugged_concrete___fusion_worktop.jpg",
    "description": "LJSTONE texture of 4033 Rugged Concrete - Fusion Worktop surface, Quartz, ICON finish, high quality stone texture."
  },
  {
    "id": "cs_62",
    "name": "511 Smokestone - Porcelain Worktop",
    "category": "Quartz",
    "texture": "Polished",
    "swatchUrl": "/stones/511_smokestone___porcelain_worktop.jpg",
    "description": "LJSTONE texture of 511 Smokestone - Porcelain Worktop surface, Quartz, Polished finish, high quality stone texture."
  },
  {
    "id": "cs_63",
    "name": "5100 Vanilla Noir - Mineral Worktop",
    "category": "Quartz",
    "texture": "Low silica",
    "swatchUrl": "/stones/5100_vanilla_noir___mineral_worktop.jpg",
    "description": "LJSTONE texture of 5100 Vanilla Noir - Mineral Worktop surface, Quartz, Low silica finish, high quality stone texture."
  },
  {
    "id": "cs_64",
    "name": "6338 Woodlands - Quartz Worktop",
    "category": "Quartz",
    "texture": "Polished",
    "swatchUrl": "/stones/6338_woodlands___quartz_worktop.jpg",
    "description": "LJSTONE texture of 6338 Woodlands - Quartz Worktop surface, Quartz, Polished finish, high quality stone texture."
  },
  {
    "id": "cs_65",
    "name": "5810 Black Tempal - Fusion Worktop",
    "category": "Quartz",
    "texture": "ICON",
    "swatchUrl": "/stones/5810_black_tempal___fusion_worktop.jpg",
    "description": "LJSTONE texture of 5810 Black Tempal - Fusion Worktop surface, Quartz, ICON finish, high quality stone texture."
  },
  {
    "id": "cs_66",
    "name": "5820 Darcrest - Quartz Worktop",
    "category": "Quartz",
    "texture": "Polished",
    "swatchUrl": "/stones/5820_darcrest___quartz_worktop.jpg",
    "description": "LJSTONE texture of 5820 Darcrest - Quartz Worktop surface, Quartz, Polished finish, high quality stone texture."
  },
  {
    "id": "cs_67",
    "name": "5101 Empira Black - Quartz Worktop",
    "category": "Quartz",
    "texture": "Polished",
    "swatchUrl": "/stones/5101_empira_black___quartz_worktop.jpg",
    "description": "LJSTONE texture of 5101 Empira Black - Quartz Worktop surface, Quartz, Polished finish, high quality stone texture."
  },
  {
    "id": "cs_68",
    "name": "514 Emprada - Porcelain Worktop",
    "category": "Quartz",
    "texture": "Polished",
    "swatchUrl": "/stones/514_emprada___porcelain_worktop.jpg",
    "description": "LJSTONE texture of 514 Emprada - Porcelain Worktop surface, Quartz, Polished finish, high quality stone texture."
  },
  {
    "id": "cs_69",
    "name": "510 Impermia - Porcelain Worktop",
    "category": "Quartz",
    "texture": "Polished",
    "swatchUrl": "/stones/510_impermia___porcelain_worktop.jpg",
    "description": "LJSTONE texture of 510 Impermia - Porcelain Worktop surface, Quartz, Polished finish, high quality stone texture."
  },
  {
    "id": "cs_70",
    "name": "3100 Jet Black - Quartz Worktop",
    "category": "Quartz",
    "texture": "Polished",
    "swatchUrl": "/stones/3100_jet_black___quartz_worktop.jpg",
    "description": "LJSTONE texture of 3100 Jet Black - Quartz Worktop surface, Quartz, Polished finish, high quality stone texture."
  },
  {
    "id": "cos_0",
    "name": "Calacatta Tova",
    "category": "Silestone - Suma",
    "texture": "Matte",
    "swatchUrl": "/stones/calacatta_tova.jpg",
    "description": "LJSTONE texture of Calacatta Tova surface, Silestone - Suma, Matte finish, high quality stone texture."
  },
  {
    "id": "cos_1",
    "name": "Bronze Rivers",
    "category": "Silestone - Suma",
    "texture": "Matte",
    "swatchUrl": "/stones/bronze_rivers.jpg",
    "description": "LJSTONE texture of Bronze Rivers surface, Silestone - Suma, Matte finish, high quality stone texture."
  },
  {
    "id": "cos_2",
    "name": "Persian White",
    "category": "Silestone - Suma",
    "texture": "Matte",
    "swatchUrl": "/stones/persian_white.jpg",
    "description": "LJSTONE texture of Persian White surface, Silestone - Suma, Matte finish, high quality stone texture."
  },
  {
    "id": "cos_3",
    "name": "Motion Grey",
    "category": "Silestone - Suma",
    "texture": "Matte",
    "swatchUrl": "/stones/motion_grey.jpg",
    "description": "LJSTONE texture of Motion Grey surface, Silestone - Suma, Matte finish, high quality stone texture."
  },
  {
    "id": "cos_4",
    "name": "Linen Cream",
    "category": "Silestone - Suma",
    "texture": "Matte",
    "swatchUrl": "/stones/linen_cream.jpg",
    "description": "LJSTONE texture of Linen Cream surface, Silestone - Suma, Matte finish, high quality stone texture."
  },
  {
    "id": "cos_5",
    "name": "Siberian",
    "category": "Silestone - Suma",
    "texture": "Matte",
    "swatchUrl": "/stones/siberian.jpg",
    "description": "LJSTONE texture of Siberian surface, Silestone - Suma, Matte finish, high quality stone texture."
  },
  {
    "id": "cos_6",
    "name": "Halcyon",
    "category": "Silestone - Nebula",
    "texture": "Matte",
    "swatchUrl": "/stones/halcyon.jpg",
    "description": "LJSTONE texture of Halcyon surface, Silestone - Nebula, Matte finish, high quality stone texture."
  },
  {
    "id": "cos_7",
    "name": "Miami Vena",
    "category": "Silestone - Nebula",
    "texture": "Matte",
    "swatchUrl": "/stones/miami_vena.jpg",
    "description": "LJSTONE texture of Miami Vena surface, Silestone - Nebula, Matte finish, high quality stone texture."
  },
  {
    "id": "cos_8",
    "name": "Lyra",
    "category": "Silestone - Nebula",
    "texture": "Matte",
    "swatchUrl": "/stones/lyra.jpg",
    "description": "LJSTONE texture of Lyra surface, Silestone - Nebula, Matte finish, high quality stone texture."
  },
  {
    "id": "cos_9",
    "name": "Lagoon",
    "category": "Silestone - Nebula",
    "texture": "Matte",
    "swatchUrl": "/stones/lagoon.jpg",
    "description": "LJSTONE texture of Lagoon surface, Silestone - Nebula, Matte finish, high quality stone texture."
  },
  {
    "id": "cos_10",
    "name": "Nara",
    "category": "Dekton - Dk Natural",
    "texture": "Matte",
    "swatchUrl": "/stones/nara.jpg",
    "description": "LJSTONE texture of Nara surface, Dekton - Dk Natural, Matte finish, high quality stone texture."
  },
  {
    "id": "cos_11",
    "name": "Kovik",
    "category": "Dekton - Dk Natural",
    "texture": "Matte",
    "swatchUrl": "/stones/kovik.jpg",
    "description": "LJSTONE texture of Kovik surface, Dekton - Dk Natural, Matte finish, high quality stone texture."
  },
  {
    "id": "cos_12",
    "name": "Aeris",
    "category": "Dekton - Dk Natural",
    "texture": "Matte",
    "swatchUrl": "/stones/aeris.jpg",
    "description": "LJSTONE texture of Aeris surface, Dekton - Dk Natural, Matte finish, high quality stone texture."
  },
  {
    "id": "cos_13",
    "name": "Eter",
    "category": "Dekton - Dk Natural",
    "texture": "Matte",
    "swatchUrl": "/stones/eter.jpg",
    "description": "LJSTONE texture of Eter surface, Dekton - Dk Natural, Matte finish, high quality stone texture."
  },
  {
    "id": "cos_14",
    "name": "Rem",
    "category": "Dekton - Dk Natural",
    "texture": "Matte",
    "swatchUrl": "/stones/rem.jpg",
    "description": "LJSTONE texture of Rem surface, Dekton - Dk Natural, Matte finish, high quality stone texture."
  },
  {
    "id": "cos_15",
    "name": "Laurent",
    "category": "Dekton - Dk Natural",
    "texture": "Matte",
    "swatchUrl": "/stones/laurent.jpg",
    "description": "LJSTONE texture of Laurent surface, Dekton - Dk Natural, Matte finish, high quality stone texture."
  },
  {
    "id": "cos_16",
    "name": "Bromo",
    "category": "Dekton - Dk Natural",
    "texture": "Matte",
    "swatchUrl": "/stones/bromo.jpg",
    "description": "LJSTONE texture of Bromo surface, Dekton - Dk Natural, Matte finish, high quality stone texture."
  },
  {
    "id": "cos_17",
    "name": "Kira",
    "category": "Dekton - Dk Natural",
    "texture": "Matte",
    "swatchUrl": "/stones/kira.jpg",
    "description": "LJSTONE texture of Kira surface, Dekton - Dk Natural, Matte finish, high quality stone texture."
  },
  {
    "id": "cos_18",
    "name": "Opera",
    "category": "Dekton - Dk Natural",
    "texture": "Matte",
    "swatchUrl": "/stones/opera.jpg",
    "description": "LJSTONE texture of Opera surface, Dekton - Dk Natural, Matte finish, high quality stone texture."
  },
  {
    "id": "cos_19",
    "name": "Entzo",
    "category": "Dekton - Dk Natural",
    "texture": "Matte",
    "swatchUrl": "/stones/entzo.jpg",
    "description": "LJSTONE texture of Entzo surface, Dekton - Dk Natural, Matte finish, high quality stone texture."
  },
  {
    "id": "cos_20",
    "name": "Kelya",
    "category": "Dekton - Dk Natural",
    "texture": "Matte",
    "swatchUrl": "/stones/kelya.jpg",
    "description": "LJSTONE texture of Kelya surface, Dekton - Dk Natural, Matte finish, high quality stone texture."
  },
  {
    "id": "cos_21",
    "name": "Aura",
    "category": "Dekton - Dk Natural",
    "texture": "Matte",
    "swatchUrl": "/stones/aura.jpg",
    "description": "LJSTONE texture of Aura surface, Dekton - Dk Natural, Matte finish, high quality stone texture."
  },
  {
    "id": "cos_22",
    "name": "Danae",
    "category": "Dekton - Dk Natural",
    "texture": "Matte",
    "swatchUrl": "/stones/danae.jpg",
    "description": "LJSTONE texture of Danae surface, Dekton - Dk Natural, Matte finish, high quality stone texture."
  },
  {
    "id": "cos_23",
    "name": "Kairos",
    "category": "Dekton - Dk Natural",
    "texture": "Matte",
    "swatchUrl": "/stones/kairos.jpg",
    "description": "LJSTONE texture of Kairos surface, Dekton - Dk Natural, Matte finish, high quality stone texture."
  },
  {
    "id": "cos_24",
    "name": "Adia",
    "category": "Dekton - Pietra Edition",
    "texture": "Matte",
    "swatchUrl": "/stones/adia.jpg",
    "description": "LJSTONE texture of Adia surface, Dekton - Pietra Edition, Matte finish, high quality stone texture."
  },
  {
    "id": "cos_25",
    "name": "Polar",
    "category": "Dekton - Pietra Edition",
    "texture": "Matte",
    "swatchUrl": "/stones/polar.jpg",
    "description": "LJSTONE texture of Polar surface, Dekton - Pietra Edition, Matte finish, high quality stone texture."
  },
  {
    "id": "cos_26",
    "name": "Sandik",
    "category": "Dekton - Pietra Edition",
    "texture": "Matte",
    "swatchUrl": "/stones/sandik.jpg",
    "description": "LJSTONE texture of Sandik surface, Dekton - Pietra Edition, Matte finish, high quality stone texture."
  },
  {
    "id": "cos_27",
    "name": "Nebu",
    "category": "Dekton - Pietra Edition",
    "texture": "Matte",
    "swatchUrl": "/stones/nebu.jpg",
    "description": "LJSTONE texture of Nebu surface, Dekton - Pietra Edition, Matte finish, high quality stone texture."
  },
  {
    "id": "cos_28",
    "name": "Trevi",
    "category": "Dekton - Pietra Edition",
    "texture": "Matte",
    "swatchUrl": "/stones/trevi.jpg",
    "description": "LJSTONE texture of Trevi surface, Dekton - Pietra Edition, Matte finish, high quality stone texture."
  },
  {
    "id": "cos_29",
    "name": "Ava",
    "category": "Dekton - Pietra Edition",
    "texture": "Matte",
    "swatchUrl": "/stones/ava.jpg",
    "description": "LJSTONE texture of Ava surface, Dekton - Pietra Edition, Matte finish, high quality stone texture."
  },
  {
    "id": "cos_30",
    "name": "Oihana",
    "category": "Sensa - Sensa Premium",
    "texture": "Matte",
    "swatchUrl": "/stones/oihana.jpg",
    "description": "LJSTONE texture of Oihana surface, Sensa - Sensa Premium, Matte finish, high quality stone texture."
  },
  {
    "id": "cos_31",
    "name": "Cristalo",
    "category": "Sensa - Sensa Premium",
    "texture": "Matte",
    "swatchUrl": "/stones/cristalo.jpg",
    "description": "LJSTONE texture of Cristalo surface, Sensa - Sensa Premium, Matte finish, high quality stone texture."
  },
  {
    "id": "cos_32",
    "name": "Itara",
    "category": "Sensa - Sensa Premium",
    "texture": "Matte",
    "swatchUrl": "/stones/itara.jpg",
    "description": "LJSTONE texture of Itara surface, Sensa - Sensa Premium, Matte finish, high quality stone texture."
  },
  {
    "id": "cos_33",
    "name": "Marau",
    "category": "Sensa - Sensa Premium",
    "texture": "Matte",
    "swatchUrl": "/stones/marau.jpg",
    "description": "LJSTONE texture of Marau surface, Sensa - Sensa Premium, Matte finish, high quality stone texture."
  },
  {
    "id": "cos_34",
    "name": "Nahoa",
    "category": "Sensa - Sensa Premium",
    "texture": "Matte",
    "swatchUrl": "/stones/nahoa.jpg",
    "description": "LJSTONE texture of Nahoa surface, Sensa - Sensa Premium, Matte finish, high quality stone texture."
  },
  {
    "id": "cos_35",
    "name": "Vancouver",
    "category": "Sensa - Sensa Premium",
    "texture": "Matte",
    "swatchUrl": "/stones/vancouver.jpg",
    "description": "LJSTONE texture of Vancouver surface, Sensa - Sensa Premium, Matte finish, high quality stone texture."
  },
  {
    "id": "cos_36",
    "name": "Platino",
    "category": "Sensa - Sensa Premium",
    "texture": "Matte",
    "swatchUrl": "/stones/platino.jpg",
    "description": "LJSTONE texture of Platino surface, Sensa - Sensa Premium, Matte finish, high quality stone texture."
  },
  {
    "id": "cos_37",
    "name": "Siberia",
    "category": "Sensa - Sensa Premium",
    "texture": "Matte",
    "swatchUrl": "/stones/siberia.jpg",
    "description": "LJSTONE texture of Siberia surface, Sensa - Sensa Premium, Matte finish, high quality stone texture."
  },
  {
    "id": "cos_38",
    "name": "Ice Blue19",
    "category": "Sensa - Sensa Premium",
    "texture": "Matte",
    "swatchUrl": "/stones/ice_blue19.jpg",
    "description": "LJSTONE texture of Ice Blue19 surface, Sensa - Sensa Premium, Matte finish, high quality stone texture."
  },
  {
    "id": "cos_39",
    "name": "Sant Angelo",
    "category": "Sensa - Sensa Premium",
    "texture": "Matte",
    "swatchUrl": "/stones/sant_angelo.jpg",
    "description": "LJSTONE texture of Sant Angelo surface, Sensa - Sensa Premium, Matte finish, high quality stone texture."
  },
  {
    "id": "cos_40",
    "name": "Nilo",
    "category": "Sensa - Sensa Premium",
    "texture": "Matte",
    "swatchUrl": "/stones/nilo.jpg",
    "description": "LJSTONE texture of Nilo surface, Sensa - Sensa Premium, Matte finish, high quality stone texture."
  },
  {
    "id": "cos_41",
    "name": "Glacial Blue",
    "category": "Sensa - Sensa Premium",
    "texture": "Matte",
    "swatchUrl": "/stones/glacial_blue.jpg",
    "description": "LJSTONE texture of Glacial Blue surface, Sensa - Sensa Premium, Matte finish, high quality stone texture."
  },
  {
    "id": "cos_42",
    "name": "Moak Black",
    "category": "Sensa - Sensa Premium",
    "texture": "Matte",
    "swatchUrl": "/stones/moak_black.jpg",
    "description": "LJSTONE texture of Moak Black surface, Sensa - Sensa Premium, Matte finish, high quality stone texture."
  },
  {
    "id": "cos_43",
    "name": "Indian Black",
    "category": "Sensa - Sensa Premium",
    "texture": "Matte",
    "swatchUrl": "/stones/indian_black.jpg",
    "description": "LJSTONE texture of Indian Black surface, Sensa - Sensa Premium, Matte finish, high quality stone texture."
  },
  {
    "id": "cos_44",
    "name": "White Macaubas",
    "category": "Sensa - Sensa Premium",
    "texture": "Matte",
    "swatchUrl": "/stones/white_macaubas.jpg",
    "description": "LJSTONE texture of White Macaubas surface, Sensa - Sensa Premium, Matte finish, high quality stone texture."
  },
  {
    "id": "cos_45",
    "name": "Black Beauty",
    "category": "Sensa - Sensa Premium",
    "texture": "Matte",
    "swatchUrl": "/stones/black_beauty.jpg",
    "description": "LJSTONE texture of Black Beauty surface, Sensa - Sensa Premium, Matte finish, high quality stone texture."
  },
  {
    "id": "cos_46",
    "name": "Colonial White",
    "category": "Sensa - Sensa Premium",
    "texture": "Matte",
    "swatchUrl": "/stones/colonial_white.jpg",
    "description": "LJSTONE texture of Colonial White surface, Sensa - Sensa Premium, Matte finish, high quality stone texture."
  },
  {
    "id": "cos_47",
    "name": "Taj Mahal",
    "category": "Sensa - Sensa Premium",
    "texture": "Matte",
    "swatchUrl": "/stones/taj_mahal.jpg",
    "description": "LJSTONE texture of Taj Mahal surface, Sensa - Sensa Premium, Matte finish, high quality stone texture."
  },
  {
    "id": "cos_48",
    "name": "Blanc Élysée",
    "category": "Silestone - Le Chic",
    "texture": "Matte",
    "swatchUrl": "/stones/blanc__lys_e.jpg",
    "description": "LJSTONE texture of Blanc Élysée surface, Silestone - Le Chic, Matte finish, high quality stone texture."
  },
  {
    "id": "cos_49",
    "name": "Jardin Emerald",
    "category": "Silestone - Le Chic",
    "texture": "Matte",
    "swatchUrl": "/stones/jardin_emerald.jpg",
    "description": "LJSTONE texture of Jardin Emerald surface, Silestone - Le Chic, Matte finish, high quality stone texture."
  },
  {
    "id": "cos_50",
    "name": "Rivière Rose",
    "category": "Silestone - Le Chic",
    "texture": "Matte",
    "swatchUrl": "/stones/rivi_re_rose.jpg",
    "description": "LJSTONE texture of Rivière Rose surface, Silestone - Le Chic, Matte finish, high quality stone texture."
  },
  {
    "id": "cos_51",
    "name": "Château Brown",
    "category": "Silestone - Le Chic",
    "texture": "Matte",
    "swatchUrl": "/stones/ch_teau_brown.jpg",
    "description": "LJSTONE texture of Château Brown surface, Silestone - Le Chic, Matte finish, high quality stone texture."
  },
  {
    "id": "cos_52",
    "name": "Ffrom03",
    "category": "Silestone - Earthic Ffrom",
    "texture": "Matte",
    "swatchUrl": "/stones/ffrom03.jpg",
    "description": "LJSTONE texture of Ffrom03 surface, Silestone - Earthic Ffrom, Matte finish, high quality stone texture."
  },
  {
    "id": "cos_53",
    "name": "Ffrom02",
    "category": "Silestone - Earthic Ffrom",
    "texture": "Matte",
    "swatchUrl": "/stones/ffrom02.jpg",
    "description": "LJSTONE texture of Ffrom02 surface, Silestone - Earthic Ffrom, Matte finish, high quality stone texture."
  },
  {
    "id": "cos_54",
    "name": "Raw A",
    "category": "Silestone - Earthic Raw",
    "texture": "Matte",
    "swatchUrl": "/stones/raw_a.jpg",
    "description": "LJSTONE texture of Raw A surface, Silestone - Earthic Raw, Matte finish, high quality stone texture."
  },
  {
    "id": "cos_55",
    "name": "Raw D",
    "category": "Silestone - Earthic Raw",
    "texture": "Matte",
    "swatchUrl": "/stones/raw_d.jpg",
    "description": "LJSTONE texture of Raw D surface, Silestone - Earthic Raw, Matte finish, high quality stone texture."
  },
  {
    "id": "cos_56",
    "name": "Raw G",
    "category": "Silestone - Earthic Raw",
    "texture": "Matte",
    "swatchUrl": "/stones/raw_g.jpg",
    "description": "LJSTONE texture of Raw G surface, Silestone - Earthic Raw, Matte finish, high quality stone texture."
  },
  {
    "id": "cos_57",
    "name": "Ffrom01",
    "category": "Silestone - Earthic Ffrom",
    "texture": "Matte",
    "swatchUrl": "/stones/ffrom01.jpg",
    "description": "LJSTONE texture of Ffrom01 surface, Silestone - Earthic Ffrom, Matte finish, high quality stone texture."
  },
  {
    "id": "cos_58",
    "name": "Negresco",
    "category": "Scalea",
    "texture": "Matte",
    "swatchUrl": "/stones/negresco.jpg",
    "description": "LJSTONE texture of Negresco surface, Scalea, Matte finish, high quality stone texture."
  },
  {
    "id": "cos_59",
    "name": "Gris Pulpis",
    "category": "Scalea",
    "texture": "Matte",
    "swatchUrl": "/stones/gris_pulpis.jpg",
    "description": "LJSTONE texture of Gris Pulpis surface, Scalea, Matte finish, high quality stone texture."
  },
  {
    "id": "cos_60",
    "name": "Perlado",
    "category": "Scalea",
    "texture": "Matte",
    "swatchUrl": "/stones/perlado.jpg",
    "description": "LJSTONE texture of Perlado surface, Scalea, Matte finish, high quality stone texture."
  },
  {
    "id": "cos_61",
    "name": "Romantic Ash",
    "category": "Silestone - Le Chic",
    "texture": "Matte",
    "swatchUrl": "/stones/romantic_ash.jpg",
    "description": "LJSTONE texture of Romantic Ash surface, Silestone - Le Chic, Matte finish, high quality stone texture."
  },
  {
    "id": "cos_62",
    "name": "Eclectic Pearl",
    "category": "Silestone - Le Chic",
    "texture": "Matte",
    "swatchUrl": "/stones/eclectic_pearl.jpg",
    "description": "LJSTONE texture of Eclectic Pearl surface, Silestone - Le Chic, Matte finish, high quality stone texture."
  },
  {
    "id": "cos_63",
    "name": "Versailles Ivory",
    "category": "Silestone - Le Chic",
    "texture": "Matte",
    "swatchUrl": "/stones/versailles_ivory.jpg",
    "description": "LJSTONE texture of Versailles Ivory surface, Silestone - Le Chic, Matte finish, high quality stone texture."
  },
  {
    "id": "cos_64",
    "name": "Bohemian Flame",
    "category": "Silestone - Le Chic",
    "texture": "Matte",
    "swatchUrl": "/stones/bohemian_flame.jpg",
    "description": "LJSTONE texture of Bohemian Flame surface, Silestone - Le Chic, Matte finish, high quality stone texture."
  },
  {
    "id": "cos_65",
    "name": "Victorian Silver",
    "category": "Silestone - Le Chic",
    "texture": "Matte",
    "swatchUrl": "/stones/victorian_silver.jpg",
    "description": "LJSTONE texture of Victorian Silver surface, Silestone - Le Chic, Matte finish, high quality stone texture."
  },
  {
    "id": "cos_66",
    "name": "Parisien Bleu",
    "category": "Silestone - Le Chic",
    "texture": "Matte",
    "swatchUrl": "/stones/parisien_bleu.jpg",
    "description": "LJSTONE texture of Parisien Bleu surface, Silestone - Le Chic, Matte finish, high quality stone texture."
  },
  {
    "id": "cos_67",
    "name": "Lime Delight",
    "category": "Silestone - Urban Crush",
    "texture": "Matte",
    "swatchUrl": "/stones/lime_delight.jpg",
    "description": "LJSTONE texture of Lime Delight surface, Silestone - Urban Crush, Matte finish, high quality stone texture."
  },
  {
    "id": "cos_68",
    "name": "Concrete Pulse",
    "category": "Silestone - Urban Crush",
    "texture": "Matte",
    "swatchUrl": "/stones/concrete_pulse.jpg",
    "description": "LJSTONE texture of Concrete Pulse surface, Silestone - Urban Crush, Matte finish, high quality stone texture."
  },
  {
    "id": "cos_69",
    "name": "Cinder Craze",
    "category": "Silestone - Urban Crush",
    "texture": "Matte",
    "swatchUrl": "/stones/cinder_craze.jpg",
    "description": "LJSTONE texture of Cinder Craze surface, Silestone - Urban Crush, Matte finish, high quality stone texture."
  },
  {
    "id": "cos_70",
    "name": "Brass Relish",
    "category": "Silestone - Urban Crush",
    "texture": "Matte",
    "swatchUrl": "/stones/brass_relish.jpg",
    "description": "LJSTONE texture of Brass Relish surface, Silestone - Urban Crush, Matte finish, high quality stone texture."
  },
  {
    "id": "cos_71",
    "name": "Grigio",
    "category": "Dekton - Pietra Kode",
    "texture": "Matte",
    "swatchUrl": "/stones/grigio.jpg",
    "description": "LJSTONE texture of Grigio surface, Dekton - Pietra Kode, Matte finish, high quality stone texture."
  },
  {
    "id": "cos_72",
    "name": "Avorio",
    "category": "Dekton - Pietra Kode",
    "texture": "Matte",
    "swatchUrl": "/stones/avorio.jpg",
    "description": "LJSTONE texture of Avorio surface, Dekton - Pietra Kode, Matte finish, high quality stone texture."
  },
  {
    "id": "cos_73",
    "name": "Grafite",
    "category": "Dekton - Pietra Kode",
    "texture": "Matte",
    "swatchUrl": "/stones/grafite.jpg",
    "description": "LJSTONE texture of Grafite surface, Dekton - Pietra Kode, Matte finish, high quality stone texture."
  },
  {
    "id": "cos_74",
    "name": "Marmorio",
    "category": "Dekton - Pietra Kode",
    "texture": "Matte",
    "swatchUrl": "/stones/marmorio.jpg",
    "description": "LJSTONE texture of Marmorio surface, Dekton - Pietra Kode, Matte finish, high quality stone texture."
  },
  {
    "id": "cos_75",
    "name": "Sabbia",
    "category": "Dekton - Pietra Kode",
    "texture": "Matte",
    "swatchUrl": "/stones/sabbia.jpg",
    "description": "LJSTONE texture of Sabbia surface, Dekton - Pietra Kode, Matte finish, high quality stone texture."
  },
  {
    "id": "cos_76",
    "name": "Dunna",
    "category": "Dekton - Dk Xgloss Basiq",
    "texture": "Matte",
    "swatchUrl": "/stones/dunna.jpg",
    "description": "LJSTONE texture of Dunna surface, Dekton - Dk Xgloss Basiq, Matte finish, high quality stone texture."
  },
  {
    "id": "cos_77",
    "name": "Nebbia",
    "category": "Dekton - Pietra Kode",
    "texture": "Matte",
    "swatchUrl": "/stones/nebbia.jpg",
    "description": "LJSTONE texture of Nebbia surface, Dekton - Pietra Kode, Matte finish, high quality stone texture."
  },
  {
    "id": "cos_78",
    "name": "Limbo",
    "category": "Dekton - Onirika",
    "texture": "Matte",
    "swatchUrl": "/stones/limbo.jpg",
    "description": "LJSTONE texture of Limbo surface, Dekton - Onirika, Matte finish, high quality stone texture."
  },
  {
    "id": "cos_79",
    "name": "Ceppo",
    "category": "Dekton - Pietra Kode",
    "texture": "Matte",
    "swatchUrl": "/stones/ceppo.jpg",
    "description": "LJSTONE texture of Ceppo surface, Dekton - Pietra Kode, Matte finish, high quality stone texture."
  },
  {
    "id": "cos_80",
    "name": "Salina",
    "category": "Dekton - Silverkoast",
    "texture": "Matte",
    "swatchUrl": "/stones/salina.jpg",
    "description": "LJSTONE texture of Salina surface, Dekton - Silverkoast, Matte finish, high quality stone texture."
  },
  {
    "id": "cos_81",
    "name": "Marina",
    "category": "Dekton - Silverkoast",
    "texture": "Matte",
    "swatchUrl": "/stones/marina.jpg",
    "description": "LJSTONE texture of Marina surface, Dekton - Silverkoast, Matte finish, high quality stone texture."
  },
  {
    "id": "cos_82",
    "name": "Malibu",
    "category": "Dekton - Silverkoast",
    "texture": "Matte",
    "swatchUrl": "/stones/malibu.jpg",
    "description": "LJSTONE texture of Malibu surface, Dekton - Silverkoast, Matte finish, high quality stone texture."
  },
  {
    "id": "cos_83",
    "name": "Albarium",
    "category": "Dekton - Kraftizen",
    "texture": "Matte",
    "swatchUrl": "/stones/albarium.jpg",
    "description": "LJSTONE texture of Albarium surface, Dekton - Kraftizen, Matte finish, high quality stone texture."
  },
  {
    "id": "cos_84",
    "name": "Somnia",
    "category": "Dekton - Onirika",
    "texture": "Matte",
    "swatchUrl": "/stones/somnia.jpg",
    "description": "LJSTONE texture of Somnia surface, Dekton - Onirika, Matte finish, high quality stone texture."
  },
  {
    "id": "cos_85",
    "name": "Awake",
    "category": "Dekton - Onirika",
    "texture": "Matte",
    "swatchUrl": "/stones/awake.jpg",
    "description": "LJSTONE texture of Awake surface, Dekton - Onirika, Matte finish, high quality stone texture."
  },
  {
    "id": "cos_86",
    "name": "Trance",
    "category": "Dekton - Onirika",
    "texture": "Matte",
    "swatchUrl": "/stones/trance.jpg",
    "description": "LJSTONE texture of Trance surface, Dekton - Onirika, Matte finish, high quality stone texture."
  },
  {
    "id": "cos_87",
    "name": "Morpheus",
    "category": "Dekton - Onirika",
    "texture": "Matte",
    "swatchUrl": "/stones/morpheus.jpg",
    "description": "LJSTONE texture of Morpheus surface, Dekton - Onirika, Matte finish, high quality stone texture."
  },
  {
    "id": "cos_88",
    "name": "Lucid",
    "category": "Dekton - Onirika",
    "texture": "Matte",
    "swatchUrl": "/stones/lucid.jpg",
    "description": "LJSTONE texture of Lucid surface, Dekton - Onirika, Matte finish, high quality stone texture."
  },
  {
    "id": "cos_89",
    "name": "Neural",
    "category": "Dekton - Onirika",
    "texture": "Matte",
    "swatchUrl": "/stones/neural.jpg",
    "description": "LJSTONE texture of Neural surface, Dekton - Onirika, Matte finish, high quality stone texture."
  },
  {
    "id": "cos_90",
    "name": "Daze",
    "category": "Dekton - Onirika",
    "texture": "Matte",
    "swatchUrl": "/stones/daze.jpg",
    "description": "LJSTONE texture of Daze surface, Dekton - Onirika, Matte finish, high quality stone texture."
  },
  {
    "id": "cos_91",
    "name": "Reverie",
    "category": "Dekton - Onirika",
    "texture": "Matte",
    "swatchUrl": "/stones/reverie.jpg",
    "description": "LJSTONE texture of Reverie surface, Dekton - Onirika, Matte finish, high quality stone texture."
  },
  {
    "id": "cos_92",
    "name": "Argentium",
    "category": "Dekton - Kraftizen",
    "texture": "Matte",
    "swatchUrl": "/stones/argentium.jpg",
    "description": "LJSTONE texture of Argentium surface, Dekton - Kraftizen, Matte finish, high quality stone texture."
  },
  {
    "id": "cos_93",
    "name": "Umber",
    "category": "Dekton - Kraftizen",
    "texture": "Matte",
    "swatchUrl": "/stones/umber.jpg",
    "description": "LJSTONE texture of Umber surface, Dekton - Kraftizen, Matte finish, high quality stone texture."
  },
  {
    "id": "cos_94",
    "name": "Nacre",
    "category": "Dekton - Kraftizen",
    "texture": "Matte",
    "swatchUrl": "/stones/nacre.jpg",
    "description": "LJSTONE texture of Nacre surface, Dekton - Kraftizen, Matte finish, high quality stone texture."
  },
  {
    "id": "cos_95",
    "name": "Ethereal Glow",
    "category": "Silestone - Ethereal",
    "texture": "Matte",
    "swatchUrl": "/stones/ethereal_glow.jpg",
    "description": "LJSTONE texture of Ethereal Glow surface, Silestone - Ethereal, Matte finish, high quality stone texture."
  },
  {
    "id": "cos_96",
    "name": "Ethereal Dusk",
    "category": "Silestone - Ethereal",
    "texture": "Matte",
    "swatchUrl": "/stones/ethereal_dusk.jpg",
    "description": "LJSTONE texture of Ethereal Dusk surface, Silestone - Ethereal, Matte finish, high quality stone texture."
  },
  {
    "id": "cos_97",
    "name": "Ethereal Haze",
    "category": "Silestone - Ethereal",
    "texture": "Matte",
    "swatchUrl": "/stones/ethereal_haze.jpg",
    "description": "LJSTONE texture of Ethereal Haze surface, Silestone - Ethereal, Matte finish, high quality stone texture."
  },
  {
    "id": "cos_98",
    "name": "Ethereal Noctis",
    "category": "Silestone - Ethereal",
    "texture": "Matte",
    "swatchUrl": "/stones/ethereal_noctis.jpg",
    "description": "LJSTONE texture of Ethereal Noctis surface, Silestone - Ethereal, Matte finish, high quality stone texture."
  },
  {
    "id": "cos_99",
    "name": "Poblenou",
    "category": "Silestone - Loft",
    "texture": "Matte",
    "swatchUrl": "/stones/poblenou.jpg",
    "description": "LJSTONE texture of Poblenou surface, Silestone - Loft, Matte finish, high quality stone texture."
  },
  {
    "id": "cos_100",
    "name": "Nolita",
    "category": "Silestone - Loft",
    "texture": "Matte",
    "swatchUrl": "/stones/nolita.jpg",
    "description": "LJSTONE texture of Nolita surface, Silestone - Loft, Matte finish, high quality stone texture."
  },
  {
    "id": "cos_101",
    "name": "Helena",
    "category": "Dekton - Stonika",
    "texture": "Matte",
    "swatchUrl": "/stones/helena.jpg",
    "description": "LJSTONE texture of Helena surface, Dekton - Stonika, Matte finish, high quality stone texture."
  },
  {
    "id": "cos_102",
    "name": "Khalo",
    "category": "Dekton - Stonika",
    "texture": "Matte",
    "swatchUrl": "/stones/khalo.jpg",
    "description": "LJSTONE texture of Khalo surface, Dekton - Stonika, Matte finish, high quality stone texture."
  },
  {
    "id": "cos_103",
    "name": "Uyuni",
    "category": "Dekton - Chromica",
    "texture": "Matte",
    "swatchUrl": "/stones/uyuni.jpg",
    "description": "LJSTONE texture of Uyuni surface, Dekton - Chromica, Matte finish, high quality stone texture."
  },
  {
    "id": "cos_104",
    "name": "Calacatta Ice",
    "category": "Scalea",
    "texture": "Matte",
    "swatchUrl": "/stones/calacatta_ice.jpg",
    "description": "LJSTONE texture of Calacatta Ice surface, Scalea, Matte finish, high quality stone texture."
  },
  {
    "id": "cos_105",
    "name": "Elegant Grey",
    "category": "Scalea",
    "texture": "Matte",
    "swatchUrl": "/stones/elegant_grey.jpg",
    "description": "LJSTONE texture of Elegant Grey surface, Scalea, Matte finish, high quality stone texture."
  },
  {
    "id": "cos_106",
    "name": "Taga",
    "category": "Dekton - Stonika",
    "texture": "Matte",
    "swatchUrl": "/stones/taga.jpg",
    "description": "LJSTONE texture of Taga surface, Dekton - Stonika, Matte finish, high quality stone texture."
  },
  {
    "id": "cos_107",
    "name": "Moone",
    "category": "Dekton - Dk Solid",
    "texture": "Matte",
    "swatchUrl": "/stones/moone.jpg",
    "description": "LJSTONE texture of Moone surface, Dekton - Dk Solid, Matte finish, high quality stone texture."
  },
  {
    "id": "cos_108",
    "name": "Et Noir",
    "category": "Silestone - Eternal",
    "texture": "Matte",
    "swatchUrl": "/stones/et_noir.jpg",
    "description": "LJSTONE texture of Et Noir surface, Silestone - Eternal, Matte finish, high quality stone texture."
  },
  {
    "id": "cos_109",
    "name": "Arga",
    "category": "Dekton - Stonika",
    "texture": "Matte",
    "swatchUrl": "/stones/arga.jpg",
    "description": "LJSTONE texture of Arga surface, Dekton - Stonika, Matte finish, high quality stone texture."
  },
  {
    "id": "cos_110",
    "name": "Crema Moca",
    "category": "Scalea",
    "texture": "Matte",
    "swatchUrl": "/stones/crema_moca.jpg",
    "description": "LJSTONE texture of Crema Moca surface, Scalea, Matte finish, high quality stone texture."
  },
  {
    "id": "cos_111",
    "name": "Belvedere",
    "category": "Scalea",
    "texture": "Matte",
    "swatchUrl": "/stones/belvedere.jpg",
    "description": "LJSTONE texture of Belvedere surface, Scalea, Matte finish, high quality stone texture."
  },
  {
    "id": "cos_112",
    "name": "Lunar",
    "category": "Dekton - Dk Industrial",
    "texture": "Matte",
    "swatchUrl": "/stones/lunar.jpg",
    "description": "LJSTONE texture of Lunar surface, Dekton - Dk Industrial, Matte finish, high quality stone texture."
  },
  {
    "id": "cos_113",
    "name": "Kreta",
    "category": "Dekton - Dk Industrial",
    "texture": "Matte",
    "swatchUrl": "/stones/kreta.jpg",
    "description": "LJSTONE texture of Kreta surface, Dekton - Dk Industrial, Matte finish, high quality stone texture."
  },
  {
    "id": "cos_114",
    "name": "Soke",
    "category": "Dekton - Dk Industrial",
    "texture": "Matte",
    "swatchUrl": "/stones/soke.jpg",
    "description": "LJSTONE texture of Soke surface, Dekton - Dk Industrial, Matte finish, high quality stone texture."
  },
  {
    "id": "cos_115",
    "name": "Desert Silver",
    "category": "Silestone - Eternal",
    "texture": "Matte",
    "swatchUrl": "/stones/desert_silver.jpg",
    "description": "LJSTONE texture of Desert Silver surface, Silestone - Eternal, Matte finish, high quality stone texture."
  },
  {
    "id": "cos_116",
    "name": "Laos",
    "category": "Dekton - Dk Industrial",
    "texture": "Matte",
    "swatchUrl": "/stones/laos.jpg",
    "description": "LJSTONE texture of Laos surface, Dekton - Dk Industrial, Matte finish, high quality stone texture."
  },
  {
    "id": "cos_117",
    "name": "Night Tebas18",
    "category": "Silestone - Mythology",
    "texture": "Matte",
    "swatchUrl": "/stones/night_tebas18.jpg",
    "description": "LJSTONE texture of Night Tebas18 surface, Silestone - Mythology, Matte finish, high quality stone texture."
  },
  {
    "id": "cos_118",
    "name": "Bianco Calacatta",
    "category": "Silestone - Eternal",
    "texture": "Matte",
    "swatchUrl": "/stones/bianco_calacatta.jpg",
    "description": "LJSTONE texture of Bianco Calacatta surface, Silestone - Eternal, Matte finish, high quality stone texture."
  },
  {
    "id": "cos_119",
    "name": "White Arabesque",
    "category": "Silestone - Nebula Alpha",
    "texture": "Matte",
    "swatchUrl": "/stones/white_arabesque.jpg",
    "description": "LJSTONE texture of White Arabesque surface, Silestone - Nebula Alpha, Matte finish, high quality stone texture."
  },
  {
    "id": "cos_120",
    "name": "Pearl Jasmine",
    "category": "Silestone - Eternal",
    "texture": "Matte",
    "swatchUrl": "/stones/pearl_jasmine.jpg",
    "description": "LJSTONE texture of Pearl Jasmine surface, Silestone - Eternal, Matte finish, high quality stone texture."
  },
  {
    "id": "cos_121",
    "name": "Charcoal Soapstone",
    "category": "Silestone - Eternal",
    "texture": "Matte",
    "swatchUrl": "/stones/charcoal_soapstone.jpg",
    "description": "LJSTONE texture of Charcoal Soapstone surface, Silestone - Eternal, Matte finish, high quality stone texture."
  },
  {
    "id": "cos_122",
    "name": "Et Marquina",
    "category": "Silestone - Eternal",
    "texture": "Matte",
    "swatchUrl": "/stones/et_marquina.jpg",
    "description": "LJSTONE texture of Et Marquina surface, Silestone - Eternal, Matte finish, high quality stone texture."
  },
  {
    "id": "cos_123",
    "name": "Miami White",
    "category": "Silestone - Mythology",
    "texture": "Matte",
    "swatchUrl": "/stones/miami_white.jpg",
    "description": "LJSTONE texture of Miami White surface, Silestone - Mythology, Matte finish, high quality stone texture."
  },
  {
    "id": "cos_124",
    "name": "Et Calacatta Gold",
    "category": "Silestone - Eternal",
    "texture": "Matte",
    "swatchUrl": "/stones/et_calacatta_gold.jpg",
    "description": "LJSTONE texture of Et Calacatta Gold surface, Silestone - Eternal, Matte finish, high quality stone texture."
  },
  {
    "id": "cos_125",
    "name": "Et Statuario",
    "category": "Silestone - Eternal",
    "texture": "Matte",
    "swatchUrl": "/stones/et_statuario.jpg",
    "description": "LJSTONE texture of Et Statuario surface, Silestone - Eternal, Matte finish, high quality stone texture."
  },
  {
    "id": "cos_126",
    "name": "Halo",
    "category": "Dekton - Dk Xgloss Solid",
    "texture": "Matte",
    "swatchUrl": "/stones/halo.jpg",
    "description": "LJSTONE texture of Halo surface, Dekton - Dk Xgloss Solid, Matte finish, high quality stone texture."
  },
  {
    "id": "cos_127",
    "name": "Trilium",
    "category": "Dekton - Dk Industrial",
    "texture": "Matte",
    "swatchUrl": "/stones/trilium.jpg",
    "description": "LJSTONE texture of Trilium surface, Dekton - Dk Industrial, Matte finish, high quality stone texture."
  },
  {
    "id": "cos_128",
    "name": "Blanco Ibiza",
    "category": "Scalea",
    "texture": "Matte",
    "swatchUrl": "/stones/blanco_ibiza.jpg",
    "description": "LJSTONE texture of Blanco Ibiza surface, Scalea, Matte finish, high quality stone texture."
  },
  {
    "id": "cos_129",
    "name": "Bergen",
    "category": "Dekton - Stonika",
    "texture": "Matte",
    "swatchUrl": "/stones/bergen.jpg",
    "description": "LJSTONE texture of Bergen surface, Dekton - Stonika, Matte finish, high quality stone texture."
  },
  {
    "id": "cos_130",
    "name": "Keon",
    "category": "Dekton - Dk Tech",
    "texture": "Matte",
    "swatchUrl": "/stones/keon.jpg",
    "description": "LJSTONE texture of Keon surface, Dekton - Dk Tech, Matte finish, high quality stone texture."
  },
  {
    "id": "cos_131",
    "name": "Snowy Ibiza",
    "category": "Silestone - Nebula Alpha",
    "texture": "Matte",
    "swatchUrl": "/stones/snowy_ibiza.jpg",
    "description": "LJSTONE texture of Snowy Ibiza surface, Silestone - Nebula Alpha, Matte finish, high quality stone texture."
  },
  {
    "id": "cos_132",
    "name": "Crema Marfil",
    "category": "Scalea",
    "texture": "Matte",
    "swatchUrl": "/stones/crema_marfil.jpg",
    "description": "LJSTONE texture of Crema Marfil surface, Scalea, Matte finish, high quality stone texture."
  },
  {
    "id": "cos_133",
    "name": "Andromeda",
    "category": "Scalea",
    "texture": "Matte",
    "swatchUrl": "/stones/andromeda.jpg",
    "description": "LJSTONE texture of Andromeda surface, Scalea, Matte finish, high quality stone texture."
  },
  {
    "id": "cos_134",
    "name": "Caliza Capri",
    "category": "Scalea",
    "texture": "Matte",
    "swatchUrl": "/stones/caliza_capri.jpg",
    "description": "LJSTONE texture of Caliza Capri surface, Scalea, Matte finish, high quality stone texture."
  },
  {
    "id": "cos_135",
    "name": "Calacatta Lincon",
    "category": "Scalea",
    "texture": "Matte",
    "swatchUrl": "/stones/calacatta_lincon.jpg",
    "description": "LJSTONE texture of Calacatta Lincon surface, Scalea, Matte finish, high quality stone texture."
  },
  {
    "id": "cos_136",
    "name": "Caliza Nevada",
    "category": "Scalea",
    "texture": "Matte",
    "swatchUrl": "/stones/caliza_nevada.jpg",
    "description": "LJSTONE texture of Caliza Nevada surface, Scalea, Matte finish, high quality stone texture."
  },
  {
    "id": "cos_137",
    "name": "Ariel",
    "category": "Silestone - Nebula Alpha",
    "texture": "Matte",
    "swatchUrl": "/stones/ariel.jpg",
    "description": "LJSTONE texture of Ariel surface, Silestone - Nebula Alpha, Matte finish, high quality stone texture."
  },
  {
    "id": "cos_138",
    "name": "Coral Clay Colour",
    "category": "Silestone - Basiq",
    "texture": "Matte",
    "swatchUrl": "/stones/coral_clay_colour.jpg",
    "description": "LJSTONE texture of Coral Clay Colour surface, Silestone - Basiq, Matte finish, high quality stone texture."
  },
  {
    "id": "cos_139",
    "name": "Blanco Maple",
    "category": "Silestone - Tropical Forest",
    "texture": "Matte",
    "swatchUrl": "/stones/blanco_maple.jpg",
    "description": "LJSTONE texture of Blanco Maple surface, Silestone - Tropical Forest, Matte finish, high quality stone texture."
  },
  {
    "id": "cos_140",
    "name": "Blanco Norte14",
    "category": "Silestone - Mythology",
    "texture": "Matte",
    "swatchUrl": "/stones/blanco_norte14.jpg",
    "description": "LJSTONE texture of Blanco Norte14 surface, Silestone - Mythology, Matte finish, high quality stone texture."
  },
  {
    "id": "cos_141",
    "name": "White Storm14",
    "category": "Silestone - Basiq",
    "texture": "Matte",
    "swatchUrl": "/stones/white_storm14.jpg",
    "description": "LJSTONE texture of White Storm14 surface, Silestone - Basiq, Matte finish, high quality stone texture."
  },
  {
    "id": "cos_142",
    "name": "Sirius",
    "category": "Dekton - Dk Solid",
    "texture": "Matte",
    "swatchUrl": "/stones/sirius.jpg",
    "description": "LJSTONE texture of Sirius surface, Dekton - Dk Solid, Matte finish, high quality stone texture."
  },
  {
    "id": "cos_143",
    "name": "Domoos",
    "category": "Dekton - Dk Solid",
    "texture": "Matte",
    "swatchUrl": "/stones/domoos.jpg",
    "description": "LJSTONE texture of Domoos surface, Dekton - Dk Solid, Matte finish, high quality stone texture."
  },
  {
    "id": "cos_144",
    "name": "Jura Blue Grey",
    "category": "Scalea",
    "texture": "Matte",
    "swatchUrl": "/stones/jura_blue_grey.jpg",
    "description": "LJSTONE texture of Jura Blue Grey surface, Scalea, Matte finish, high quality stone texture."
  },
  {
    "id": "cos_145",
    "name": "Stellar Blanco13",
    "category": "Silestone - Stellar",
    "texture": "Matte",
    "swatchUrl": "/stones/stellar_blanco13.jpg",
    "description": "LJSTONE texture of Stellar Blanco13 surface, Silestone - Stellar, Matte finish, high quality stone texture."
  },
  {
    "id": "cos_146",
    "name": "Zenith",
    "category": "Dekton - Dk Solid",
    "texture": "Matte",
    "swatchUrl": "/stones/zenith.jpg",
    "description": "LJSTONE texture of Zenith surface, Dekton - Dk Solid, Matte finish, high quality stone texture."
  },
  {
    "id": "cos_147",
    "name": "White Zeus",
    "category": "Silestone - Mythology",
    "texture": "Matte",
    "swatchUrl": "/stones/white_zeus.jpg",
    "description": "LJSTONE texture of White Zeus surface, Silestone - Mythology, Matte finish, high quality stone texture."
  },
  {
    "id": "cos_148",
    "name": "Gris Expo",
    "category": "Silestone - Mythology",
    "texture": "Matte",
    "swatchUrl": "/stones/gris_expo.jpg",
    "description": "LJSTONE texture of Gris Expo surface, Silestone - Mythology, Matte finish, high quality stone texture."
  },
  {
    "id": "cos_149",
    "name": "Marengo",
    "category": "Silestone - Basiq",
    "texture": "Matte",
    "swatchUrl": "/stones/marengo.jpg",
    "description": "LJSTONE texture of Marengo surface, Silestone - Basiq, Matte finish, high quality stone texture."
  }
]